<annotation>
	<folder></folder>
	<filename>chess--64-_jpg.rf.cbac79290ff46f6dd63808a2656f4047.jpg</filename>
	<path>chess--64-_jpg.rf.cbac79290ff46f6dd63808a2656f4047.jpg</path>
	<source>
		<database>roboflow.ai</database>
	</source>
	<size>
		<width>416</width>
		<height>416</height>
		<depth>3</depth>
	</size>
	<segmented>0</segmented>
	<object>
		<name>white-rook</name>
		<pose>Unspecified</pose>
		<truncated>0</truncated>
		<difficult>0</difficult>
		<occluded>0</occluded>
		<bndbox>
			<xmin>143</xmin>
			<xmax>178</xmax>
			<ymin>34</ymin>
			<ymax>73</ymax>
		</bndbox>
	</object>
	<object>
		<name>white-rook</name>
		<pose>Unspecified</pose>
		<truncated>0</truncated>
		<difficult>0</difficult>
		<occluded>0</occluded>
		<bndbox>
			<xmin>227</xmin>
			<xmax>265</xmax>
			<ymin>34</ymin>
			<ymax>76</ymax>
		</bndbox>
	</object>
	<object>
		<name>black-rook</name>
		<pose>Unspecified</pose>
		<truncated>0</truncated>
		<difficult>0</difficult>
		<occluded>0</occluded>
		<bndbox>
			<xmin>22</xmin>
			<xmax>48</xmax>
			<ymin>33</ymin>
			<ymax>74</ymax>
		</bndbox>
	</object>
	<object>
		<name>black-queen</name>
		<pose>Unspecified</pose>
		<truncated>0</truncated>
		<difficult>0</difficult>
		<occluded>0</occluded>
		<bndbox>
			<xmin>149</xmin>
			<xmax>178</xmax>
			<ymin>233</ymin>
			<ymax>277</ymax>
		</bndbox>
	</object>
	<object>
		<name>black-bishop</name>
		<pose>Unspecified</pose>
		<truncated>0</truncated>
		<difficult>0</difficult>
		<occluded>0</occluded>
		<bndbox>
			<xmin>120</xmin>
			<xmax>145</xmax>
			<ymin>242</ymin>
			<ymax>273</ymax>
		</bndbox>
	</object>
	<object>
		<name>black-rook</name>
		<pose>Unspecified</pose>
		<truncated>0</truncated>
		<difficult>0</difficult>
		<occluded>0</occluded>
		<bndbox>
			<xmin>197</xmin>
			<xmax>221</xmax>
			<ymin>240</ymin>
			<ymax>277</ymax>
		</bndbox>
	</object>
	<object>
		<name>white-bishop</name>
		<pose>Unspecified</pose>
		<truncated>0</truncated>
		<difficult>0</difficult>
		<occluded>0</occluded>
		<bndbox>
			<xmin>32</xmin>
			<xmax>58</xmax>
			<ymin>239</ymin>
			<ymax>279</ymax>
		</bndbox>
	</object>
	<object>
		<name>black-knight</name>
		<pose>Unspecified</pose>
		<truncated>0</truncated>
		<difficult>0</difficult>
		<occluded>0</occluded>
		<bndbox>
			<xmin>245</xmin>
			<xmax>274</xmax>
			<ymin>284</ymin>
			<ymax>321</ymax>
		</bndbox>
	</object>
	<object>
		<name>white-knight</name>
		<pose>Unspecified</pose>
		<truncated>0</truncated>
		<difficult>0</difficult>
		<occluded>0</occluded>
		<bndbox>
			<xmin>123</xmin>
			<xmax>147</xmax>
			<ymin>285</ymin>
			<ymax>323</ymax>
		</bndbox>
	</object>
	<object>
		<name>white-pawn</name>
		<pose>Unspecified</pose>
		<truncated>0</truncated>
		<difficult>0</difficult>
		<occluded>0</occluded>
		<bndbox>
			<xmin>71</xmin>
			<xmax>93</xmax>
			<ymin>292</ymin>
			<ymax>319</ymax>
		</bndbox>
	</object>
	<object>
		<name>black-bishop</name>
		<pose>Unspecified</pose>
		<truncated>0</truncated>
		<difficult>0</difficult>
		<occluded>0</occluded>
		<bndbox>
			<xmin>1</xmin>
			<xmax>20</xmax>
			<ymin>296</ymin>
			<ymax>330</ymax>
		</bndbox>
	</object>
	<object>
		<name>white-pawn</name>
		<pose>Unspecified</pose>
		<truncated>0</truncated>
		<difficult>0</difficult>
		<occluded>0</occluded>
		<bndbox>
			<xmin>194</xmin>
			<xmax>219</xmax>
			<ymin>332</ymin>
			<ymax>358</ymax>
		</bndbox>
	</object>
	<object>
		<name>white-pawn</name>
		<pose>Unspecified</pose>
		<truncated>0</truncated>
		<difficult>0</difficult>
		<occluded>0</occluded>
		<bndbox>
			<xmin>73</xmin>
			<xmax>95</xmax>
			<ymin>334</ymin>
			<ymax>359</ymax>
		</bndbox>
	</object>
	<object>
		<name>white-pawn</name>
		<pose>Unspecified</pose>
		<truncated>0</truncated>
		<difficult>0</difficult>
		<occluded>0</occluded>
		<bndbox>
			<xmin>203</xmin>
			<xmax>226</xmax>
			<ymin>378</ymin>
			<ymax>404</ymax>
		</bndbox>
	</object>
	<object>
		<name>black-knight</name>
		<pose>Unspecified</pose>
		<truncated>0</truncated>
		<difficult>0</difficult>
		<occluded>0</occluded>
		<bndbox>
			<xmin>160</xmin>
			<xmax>186</xmax>
			<ymin>378</ymin>
			<ymax>410</ymax>
		</bndbox>
	</object>
	<object>
		<name>white-king</name>
		<pose>Unspecified</pose>
		<truncated>0</truncated>
		<difficult>0</difficult>
		<occluded>0</occluded>
		<bndbox>
			<xmin>115</xmin>
			<xmax>146</xmax>
			<ymin>375</ymin>
			<ymax>414</ymax>
		</bndbox>
	</object>
	<object>
		<name>black-pawn</name>
		<pose>Unspecified</pose>
		<truncated>0</truncated>
		<difficult>0</difficult>
		<occluded>0</occluded>
		<bndbox>
			<xmin>72</xmin>
			<xmax>98</xmax>
			<ymin>383</ymin>
			<ymax>408</ymax>
		</bndbox>
	</object>
	<object>
		<name>white-pawn</name>
		<pose>Unspecified</pose>
		<truncated>0</truncated>
		<difficult>0</difficult>
		<occluded>0</occluded>
		<bndbox>
			<xmin>285</xmin>
			<xmax>314</xmax>
			<ymin>257</ymin>
			<ymax>292</ymax>
		</bndbox>
	</object>
	<object>
		<name>white-pawn</name>
		<pose>Unspecified</pose>
		<truncated>0</truncated>
		<difficult>0</difficult>
		<occluded>0</occluded>
		<bndbox>
			<xmin>327</xmin>
			<xmax>355</xmax>
			<ymin>260</ymin>
			<ymax>295</ymax>
		</bndbox>
	</object>
	<object>
		<name>white-pawn</name>
		<pose>Unspecified</pose>
		<truncated>0</truncated>
		<difficult>0</difficult>
		<occluded>0</occluded>
		<bndbox>
			<xmin>369</xmin>
			<xmax>398</xmax>
			<ymin>259</ymin>
			<ymax>293</ymax>
		</bndbox>
	</object>
	<object>
		<name>white-pawn</name>
		<pose>Unspecified</pose>
		<truncated>0</truncated>
		<difficult>0</difficult>
		<occluded>0</occluded>
		<bndbox>
			<xmin>408</xmin>
			<xmax>416</xmax>
			<ymin>255</ymin>
			<ymax>291</ymax>
		</bndbox>
	</object>
	<object>
		<name>black-pawn</name>
		<pose>Unspecified</pose>
		<truncated>0</truncated>
		<difficult>0</difficult>
		<occluded>0</occluded>
		<bndbox>
			<xmin>367</xmin>
			<xmax>393</xmax>
			<ymin>306</ymin>
			<ymax>337</ymax>
		</bndbox>
	</object>
	<object>
		<name>black-pawn</name>
		<pose>Unspecified</pose>
		<truncated>0</truncated>
		<difficult>0</difficult>
		<occluded>0</occluded>
		<bndbox>
			<xmin>328</xmin>
			<xmax>350</xmax>
			<ymin>305</ymin>
			<ymax>335</ymax>
		</bndbox>
	</object>
	<object>
		<name>black-pawn</name>
		<pose>Unspecified</pose>
		<truncated>0</truncated>
		<difficult>0</difficult>
		<occluded>0</occluded>
		<bndbox>
			<xmin>286</xmin>
			<xmax>312</xmax>
			<ymin>300</ymin>
			<ymax>328</ymax>
		</bndbox>
	</object>
</annotation>
